{
  "timestamp": "2025-08-26T19:17:44.340839",
  "ticker": "^VIX",
  "data_points": 2475,
  "latest_signal": {
    "date": "2025-08-25",
    "signal": "HOLD",
    "position": "FLAT",
    "phase_quadrant": "Quadrante 4 (Discesa -> Minimo)",
    "phase_value": 1.779487539629354,
    "oscillator_value": -1.08774995803833,
    "signal_strength": 13.909046148207603,
    "confidence": "LOW",
    "price": 14.789999961853027,
    "timestamp": "2025-08-26T19:17:43.002296"
  },
  "backtest_metrics": {
    "total_return_%": 237.87931218836115,
    "max_drawdown_%": 4.518346422995546,
    "sharpe_ratio": 1.420295659013899,
    "sortino_ratio": 3.122609516886435,
    "calmar_ratio": 10.106753054631797,
    "total_trades": 17,
    "win_rate_%": 64.70588235294117,
    "profit_factor": 15.230529988659711
  },
  "cycle_analysis": {
    "dominant_period": 84.0,
    "p_value": 0.0,
    "significant": "True"
  }
}