{
  "timestamp": "2026-04-21T22:05:11.089051",
  "ticker": "^VIX",
  "data_points": 5104,
  "latest_signal": {
    "date": "2026-04-21",
    "signal": "HOLD",
    "position": "LONG",
    "phase_quadrant": "Quadrante 1 (Minimo -> Salita)",
    "phase_value": -2.6013182339751597,
    "oscillator_value": -4.2464999198913596,
    "signal_strength": 2.057849578970047,
    "confidence": "LOW",
    "price": 19.5,
    "timestamp": "2026-04-21T22:05:08.774627"
  },
  "backtest_metrics": {
    "total_return_%": 428.52151419356045,
    "max_drawdown_%": 47.6587401268174,
    "sharpe_ratio": 0.720266484539546,
    "sortino_ratio": 1.138706918644032,
    "calmar_ratio": 0.9766303786953892,
    "total_trades": 21,
    "win_rate_%": 76.19047619047619,
    "profit_factor": 8.052552311601497
  },
  "cycle_analysis": {
    "dominant_period": 84.0,
    "p_value": 0.0,
    "significant": "True"
  }
}