{
  "timestamp": "2025-10-23T21:33:59.549826",
  "ticker": "^VIX",
  "data_points": 5031,
  "latest_signal": {
    "date": "2025-10-22",
    "signal": "HOLD",
    "position": "FLAT",
    "phase_quadrant": "Quadrante 3 (Picco -> Discesa)",
    "phase_value": 0.3728553714320935,
    "oscillator_value": 3.067999982833861,
    "signal_strength": 8.217884683553242,
    "confidence": "LOW",
    "price": 18.600000381469727,
    "timestamp": "2025-10-23T21:33:57.859904"
  },
  "backtest_metrics": {
    "total_return_%": 925.8449282470551,
    "max_drawdown_%": 0.9152732673729622,
    "sharpe_ratio": 0.48314776118630626,
    "sortino_ratio": 14.230158069836074,
    "calmar_ratio": 86.36434567883252,
    "total_trades": 27,
    "win_rate_%": 85.18518518518519,
    "profit_factor": 69.21107450349605
  },
  "cycle_analysis": {
    "dominant_period": 84.0,
    "p_value": 0.0,
    "significant": "True"
  }
}